nautobot_netbox_importer/__init__.py
nautobot_netbox_importer/app-config-schema.json
nautobot_netbox_importer/base.py
nautobot_netbox_importer/command_utils.py
nautobot_netbox_importer/diffsync/__init__.py
nautobot_netbox_importer/diffsync/adapters/__init__.py
nautobot_netbox_importer/diffsync/adapters/nautobot.py
nautobot_netbox_importer/diffsync/adapters/netbox.py
nautobot_netbox_importer/diffsync/models/__init__.py
nautobot_netbox_importer/diffsync/models/base.py
nautobot_netbox_importer/diffsync/models/cables.py
nautobot_netbox_importer/diffsync/models/circuits.py
nautobot_netbox_importer/diffsync/models/content_types.py
nautobot_netbox_importer/diffsync/models/custom_fields.py
nautobot_netbox_importer/diffsync/models/dcim.py
nautobot_netbox_importer/diffsync/models/ipam.py
nautobot_netbox_importer/diffsync/models/locations.py
nautobot_netbox_importer/diffsync/models/object_change.py
nautobot_netbox_importer/diffsync/models/tags.py
nautobot_netbox_importer/diffsync/models/virtualization.py
nautobot_netbox_importer/generator/__init__.py
nautobot_netbox_importer/generator/base.py
nautobot_netbox_importer/generator/exceptions.py
nautobot_netbox_importer/generator/fields.py
nautobot_netbox_importer/generator/nautobot.py
nautobot_netbox_importer/generator/source.py
nautobot_netbox_importer/management/commands/import_netbox.py
nautobot_netbox_importer/static/nautobot_netbox_importer/docs/404.html
nautobot_netbox_importer/static/nautobot_netbox_importer/docs/admin/compatibility_matrix.html
nautobot_netbox_importer/static/nautobot_netbox_importer/docs/admin/install.html
nautobot_netbox_importer/static/nautobot_netbox_importer/docs/admin/release_notes/index.html
nautobot_netbox_importer/static/nautobot_netbox_importer/docs/admin/release_notes/version_1.0.html
nautobot_netbox_importer/static/nautobot_netbox_importer/docs/admin/release_notes/version_1.1.html
nautobot_netbox_importer/static/nautobot_netbox_importer/docs/admin/release_notes/version_1.2.html
nautobot_netbox_importer-2.2.0.dist-info/LICENSE
nautobot_netbox_importer-2.2.0.dist-info/METADATA
nautobot_netbox_importer-2.2.0.dist-info/WHEEL
nautobot_netbox_importer-2.2.0.dist-info/RECORD
