Metadata-Version: 2.1
Name: nautobot-netbox-importer
Version: 2.2.0
Summary: Data importer from NetBox 3.x to Nautobot 2.x.
Home-page: https://github.com/nautobot/nautobot-app-netbox-importer
License: Apache-2.0
Keywords: nautobot,nautobot-app,nautobot-plugin
Author: Network to Code, LLC
Author-email: opensource@networktocode.com
Requires-Python: >=3.9.2,<3.13
Classifier: Development Status :: 5 - Production/Stable
Classifier: Intended Audience :: Developers
Classifier: License :: OSI Approved :: Apache Software License
Classifier: Programming Language :: Python :: 3
Classifier: Programming Language :: Python :: 3.10
Classifier: Programming Language :: Python :: 3.11
Classifier: Programming Language :: Python :: 3.12
Classifier: Programming Language :: Python :: 3.8
Classifier: Programming Language :: Python :: 3.9
Provides-Extra: all
Requires-Dist: Markdown (>=3.6,<4.0)
Requires-Dist: colorama (>=0.4.6,<0.5.0)
Requires-Dist: diffsync (>=2.1.0,<3.0.0)
Requires-Dist: ijson (>=3.2.3,<4.0.0)
Requires-Dist: nautobot (>=2.4.9,<3.0.0)
Requires-Dist: netaddr (>=0.10.1)
Requires-Dist: packaging (>=24.1,<25.0)
Requires-Dist: pydantic (>=2.11.5,<3.0.0)
Requires-Dist: python-dateutil (>=2.9.0,<3.0.0)
Project-URL: Documentation, https://docs.nautobot.com/projects/netbox-importer/en/latest/
Project-URL: Repository, https://github.com/nautobot/nautobot-app-netbox-importer
